[
    {
        "text": "之《黄帝内经》与《本草纲目》"
    },
    {
        "text": "主讲人李鸿涛"
    },
    {
        "text": "中医古籍是一个伟大的宝库"
    },
    {
        "text": "一、中医古籍是一个伟大的宝库"
    },
    {
        "text": "◇中国是一个拥有5000年灿烂文化和56个民族的多民族国家，各民族在与疾病的长期抗争中，创立了具有本民族特色的医药体系，中医、藏医、维医、蒙医、傣医、苗医等相互借鉴、互相通融，共同构成了荟萃各民族医药精华的中国传统医药体系，而中医学是中国传统医药体系中的杰出代表。"
    },
    {
        "text": "一、中医古籍是一个伟大的宝库"
    },
    {
        "text": "◇古籍是指书写或印刷于1912年以前，具有中国古典装帧形式的中国古代书籍。◇中医古籍产生于秦汉之前，形成于隋唐之际，发展于宋元之后，绵延2000多年，形成了中国独有的伟大的宝库，也是承载人类文明记忆的重要载体。"
    },
    {
        "text": "一、中医古籍是一个伟大的宝库"
    },
    {
        "text": "◇据2005年的第3次中医古籍资源调查情况统计，中国国内150家图书馆收藏有中医古籍近9000种。◇据海外中医古籍调研项目统计，海外11个国家和2个地区的137个图书馆收藏有大量中医药典籍，其中有些珍稀品种在国内已经失传。"
    },
    {
        "text": "一、中医古籍是一个伟大的宝库"
    },
    {
        "text": "中医古籍记录了中医学数千年来积累的丰富理论知识和临床经验，不仅具有珍贵的文物价值，而且具有重要的学术价值。"
    },
    {
        "text": "◇珍贵的中医药古籍蕴含着具有原创优势的宝贵经验与医学知识。"
    },
    {
        "text": "◇也是承载中华民族优秀文化和实用技术的重要载体之一。"
    },
    {
        "text": "一、中医古籍是一个伟大的宝库"
    },
    {
        "text": "作为中医古籍中的杰出代表，《黄帝内经》《本草纲目》承载了中医、中药灿烂辉煌的文明与科学内涵。2011年5月25日，在英国曼彻斯特召开的联合国教科文组织世界记忆工程国际咨询委员会（IAC）第十次会议上，由世界记忆工程中国国家委员会申报的两部“中国传统医药档案文献”《黄帝内经》和《本草纲目》顺利通过评审，并经联合国教科文组织批准列入《世界记忆名录》（MemoryoftheWorldRegister）。"
    },
    {
        "text": "《黄帝内经》《本草纲目》是《世界记忆名录》的杰出代表"
    },
    {
        "text": "二、《黄帝内经》《本草纲目》是《世界记忆名录》的杰出代表"
    },
    {
        "text": "二、《黄帝内经》《本草纲目》是《世界记忆名录》的杰出代表"
    },
    {
        "text": "◇世界记忆工程是联合国教科文组织于1992年发起的，旨在实施联合国教科文组织宪章中规定的保护世界文化遗产的任务，促进文化遗产利用，提高人们对文献遗产的重要性的认识。具体讲就是手稿、图书馆和档案馆保存的任何介质的珍贵文献以及口述历史记录等。◇《黄帝内经》《本草纲目》成功入选《世界记忆名录》为中医文献原创价值和科技内涵的认知在国际上赢得一席之地，扩大了在世界范围的影响。"
    },
    {
        "text": "《黄帝内经》与《本草纲目》的成就与贡献"
    },
    {
        "text": "三、《黄帝内经》与《本草纲目》的成就与贡献"
    },
    {
        "text": "（一）《黄帝内经》"
    },
    {
        "text": "三、《黄帝内经》与《本草纲目》的成就与贡献"
    },
    {
        "text": "1.主要内容"
    },
    {
        "text": "三、《黄帝内经》与《本草纲目》的成就与贡献"
    },
    {
        "text": "2.科学内涵及意义"
    },
    {
        "text": "《黄帝内经》总结了公元前2世纪以前传统医学的成就，集中代表了这一时代的医学理论和治疗经验，并提出重要的预防医学思想，他所构建的医疗模式和理论体系至今仍然被传统医药学运用和西方医学的借鉴，因此，此书是传统医药的重要奠基之作，具有任何医学著作无可比拟的作用。"
    },
    {
        "text": "三、《黄帝内经》与《本草纲目》的成就与贡献"
    },
    {
        "text": "2.科学内涵及意义"
    },
    {
        "text": "《黄帝内经》中记述的医学理论体系涵盖了公元前2世纪以前中国周边国家和地区传统医学的成就，其中所提出的医学理论体系以及以针灸为代表的传统医学疗法，在成书后的2000余年来，仍然有效的指导着以中医学为起源的传统医学，并且在《黄帝内经》构建的理论基础之上所衍化、派生出来的诸多传统医学，至今仍有效的在医学实践中应用。其思维方法和原则，正在成为当今世界医学发展的主题，被世界卫生组织所提倡和推广。"
    },
    {
        "text": "三、《黄帝内经》与《本草纲目》的成就与贡献"
    },
    {
        "text": "2.科学内涵及意义"
    },
    {
        "text": "《黄帝内经》为2200年前众多的中国科学家相继编写而成。因黄帝被誉为中国古代科学技术、东方文明的开创者和杰出代表，本书便以黄帝为名，以体现其凝聚力、影响力和权威性、重要性。"
    },
    {
        "text": "三、《黄帝内经》与《本草纲目》的成就与贡献"
    },
    {
        "text": "2.科学内涵及意义"
    },
    {
        "text": "《黄帝内经》自公元前2世纪形成后，先后以竹简、缣帛、纸为载体流传，至1339年由中国元朝的胡氏古林书堂印刷出版，此后陆续整理、修订。此书为当今世界上保存完好的版本，历经600余年，屡经各个时代的收藏家收藏，至公元20世纪由中国国家图书馆收藏，保存至今。"
    },
    {
        "text": "三、《黄帝内经》与《本草纲目》的成就与贡献"
    },
    {
        "text": "2.科学内涵及意义"
    },
    {
        "text": "三、《黄帝内经》与《本草纲目》的成就与贡献"
    },
    {
        "text": "（二）本草纲目"
    },
    {
        "text": "三、《黄帝内经》与《本草纲目》的成就与贡献"
    },
    {
        "text": "1.主要内容"
    },
    {
        "text": "三、《黄帝内经》与《本草纲目》的成就与贡献"
    },
    {
        "text": "2.科学内涵及意义"
    },
    {
        "text": "《本草纲目》记载与总结了中国16世纪以前传统药物学成就。其改进了传统的药物分类法，提高了生物学分类的科学性，是当时世界上最先进的分类方式。李时珍对世界科学的贡献足以与同时代的欧洲文艺复兴时期最好的科学家相比，而《本草纲目》本身亦不失为从中世纪科学向近代科学转型时期具有近代科学精神的最高水平的古典科学杰作。"
    },
    {
        "text": "三、《黄帝内经》与《本草纲目》的成就与贡献"
    },
    {
        "text": "2.科学内涵及意义"
    },
    {
        "text": "《本草纲目》不仅记载了16世纪以前中国的药物资源，还记载了一些从海外传入的天然药物及其相关知识，例如波斯、印度及地中海等地区。《本草纲目》对世界自然科学也有举世瞩目的公认贡献。"
    },
    {
        "text": "三、《黄帝内经》与《本草纲目》的成就与贡献"
    },
    {
        "text": "2.科学内涵及意义"
    },
    {
        "text": "◇李时珍（1518-1593）◇是中国历史上伟大的医学家和药物学家。◇他30年的研究工作凝聚成了史诗般的巨著《本草纲目》，这是他对医学的突出贡献。◇还撰写了其余11部医学著作，如《濒湖脉学》、《奇经八脉考》等。"
    },
    {
        "text": "三、《黄帝内经》与《本草纲目》的成就与贡献"
    },
    {
        "text": "2.科学内涵及意义"
    },
    {
        "text": "1593年版《本草纲目》是世界现存的《本草纲目》稀有版本，为1593年金陵（现南京）胡承龙刊刻，出版印刷400余年以来，所存无几，是中国保存最完好的版本，也是自本书16世纪成书以后古今中外出版的《本草纲目》的祖本。"
    },
    {
        "text": "三、《黄帝内经》与《本草纲目》的成就与贡献"
    },
    {
        "text": "◇《本草纲目》是中国医药史上的集大成之作，并在世界上卓有影响。◇英国生物学家达尔文认为它是“中国古代的百科全书”。◇英国著名科学史家李约瑟在其《中国科学技术史》第一卷中，对李时珍及其《本草纲目》作了这样的评价，“毫无疑问，明代最伟大的科学成就，是李时珍那部在本草书中登峰造极的著作《本草纲目》。李时珍作为科学家，达到了同伽里略、维萨里的科学活动隔绝的任何人所不能达到的最高水平。”"
    }
]