[
    {
        "text": "题干内容: 全球出版发行量第二，仅次于《圣经》的经典是_。?选项答案:《老子》;"
    },
    {
        "text": "题干内容: 中国的绘画讲究_，虚实相生，无画之处皆成妙境。?选项答案:留白;"
    },
    {
        "text": "题干内容: 含德之厚，比于_。（《老子·五十五章》）?选项答案:赤子;"
    },
    {
        "text": "题干内容: 以下“无为而治”的两个典型治世是：_?选项答案:文景之治贞观之治;"
    },
    {
        "text": "题干内容: 故坚强者死之徒，_生之徒。（《老子》）?选项答案:柔弱者;"
    },
    {
        "text": "题干内容: 质胜文则野，文胜质则史，_，然后君子。《论语・雍也》【注释】质朴胜过文采就粗野，文采胜过质朴就死板，文采质朴结合匀称，形式内容相得益彰，才是君子。按：“质胜文”近似动物，但有生命；“文胜质”如同机器，更为可怖。孔子言“仁”居功至伟者，就是使人不做动物又非机器。?选项答案:文质彬彬;"
    },
    {
        "text": "题干内容: 用五个字概括老子的辩证法：（）。小注：钱钟书先生认为这五个字抵得上黑格尔的千言万语。?选项答案:反者道之动;"
    },
    {
        "text": "题干内容: 圣人后其身而身先，外其身而身存。——（《道德经》第七章）中国武侠小说中的高手过招，胜利者会真诚道一句“()！”，谦虚地表示“承蒙您相让，使我优先”。圣人更是如此，“后其身”、“外其身”舍弃小我而成就大我。世间万事万物都处在变化之中，“弱者，道之用”。唯有“慈、俭、不敢为天下先”的厚德之人才与道最近。古人云“水唯善下方成海，山不矜高自及天”。?选项答案:承让;"
    },
    {
        "text": "题干内容: 用一个成语概括以下段落_选自北宋大儒张载的《西铭》——乾称父，坤称母；(以天为父，以地为母。)予兹藐焉，乃混然中处。（我啊，是那样的渺小，与天地混合，处于天地之中。）故天地之塞，吾其体；（所以啊，充塞于天地间的是乾坤阴阳二气，我也以此乾坤阴阳二气为体。）天地之帅，吾其性。（阴阳二气所遵循的天地之乾健坤顺的性质，我也以此成就了自己的本性。）民，吾同胞；物，吾与也。（大地众生皆是如此，所以啊，人民是我的同胞，万物是我的同类）?选项答案:民胞物与;"
    },
    {
        "text": "题干内容: 人法地，地法天，天法道，道法（）——《道德经·第二十五章》?选项答案:自然;"
    }
]